octopus/__init__.py
octopus/octopus_eth_evm.py
octopus/analysis/__init__.py
octopus/analysis/cfg.py
octopus/analysis/graph.py
octopus/arch/__init__.py
octopus/arch/evm/__init__.py
octopus/arch/evm/cfg.py
octopus/arch/evm/disassembler.py
octopus/arch/evm/emulator.py
octopus/arch/evm/evm.py
octopus/arch/evm/instruction.py
octopus/arch/evm/signatures.json
octopus/arch/evm/ssa.py
octopus/arch/evm/vmstate.py
octopus/arch/wasm/__init__.py
octopus/arch/wasm/analyzer.py
octopus/arch/wasm/cfg.py
octopus/arch/wasm/constant.py
octopus/arch/wasm/decode.py
octopus/arch/wasm/disassembler.py
octopus/arch/wasm/emulator.py
octopus/arch/wasm/format.py
octopus/arch/wasm/instruction.py
octopus/arch/wasm/vmstate.py
octopus/arch/wasm/wasm.py
octopus/core/__init__.py
octopus/core/basicblock.py
octopus/core/contract.py
octopus/core/edge.py
octopus/core/function.py
octopus/core/instruction.py
octopus/core/ssa.py
octopus/core/utils.py
octopus/engine/__init__.py
octopus/engine/disassembler.py
octopus/engine/emulator.py
octopus/engine/engine.py
octopus/engine/explorer.py
octopus/engine/helper.py
octopus/engine/ssa.py
octopus/engine/symbolic_execution.py
octopus/platforms/__init__.py
octopus/platforms/BTC/__init__.py
octopus/platforms/BTC/bech32.py
octopus/platforms/BTC/btcscript.py
octopus/platforms/BTC/disassembler.py
octopus/platforms/BTC/explorer.py
octopus/platforms/BTC/instruction.py
octopus/platforms/EOS/__init__.py
octopus/platforms/EOS/analyzer.py
octopus/platforms/EOS/cfg.py
octopus/platforms/EOS/disassembler.py
octopus/platforms/EOS/emulator.py
octopus/platforms/EOS/explorer.py
octopus/platforms/ETH/__init__.py
octopus/platforms/ETH/cfg.py
octopus/platforms/ETH/constants.py
octopus/platforms/ETH/contract.py
octopus/platforms/ETH/disassembler.py
octopus/platforms/ETH/emulator.py
octopus/platforms/ETH/explorer.py
octopus/platforms/ETH/save_ssa.py
octopus/platforms/ETH/util.py
octopus/platforms/NEO/__init__.py
octopus-0.3.4.dist-info/METADATA
octopus-0.3.4.dist-info/RECORD
octopus-0.3.4.dist-info/WHEEL
octopus-0.3.4.dist-info/entry_points.txt
octopus-0.3.4.dist-info/top_level.txt
