Metadata-Version: 2.1
Name: octopus
Version: 0.3.4
Summary: Security analysis framework for WebAssembly module (wasm) and Blockchain Smart Contract (BTC/ETH/EOS/NEO).
Home-page: https://github.com/quoscient/octopus
Author: QuoScient
License: MIT
Keywords: disassembler security webassembly ethereum eos neo
Platform: UNKNOWN
Classifier: Development Status :: 3 - Alpha
Classifier: Intended Audience :: Science/Research
Classifier: Topic :: Software Development :: Disassemblers
Classifier: License :: OSI Approved :: MIT License
Classifier: Programming Language :: Python :: 3.5
Classifier: Programming Language :: Python :: 3.6
Classifier: Programming Language :: Python :: 3.7
Requires-Python: >=3.5
Requires-Dist: z3-solver (>=4.5)
Requires-Dist: requests (>=2.18.4)
Requires-Dist: graphviz (>=0.8.3)
Requires-Dist: wasm (>=1.1)
